pythonji/__init__.py
pythonji/__main__.py
pythonji-0.1.1.dist-info/entry_points.txt
pythonji-0.1.1.dist-info/LICENSE
pythonji-0.1.1.dist-info/WHEEL
pythonji-0.1.1.dist-info/METADATA
pythonji-0.1.1.dist-info/RECORD
